[
    {
        "local": [
            {
                "user": {
                    "name": "{0}",
                    "email": "{1}"
                }, 
                "projects": [
                    {
                        "name": "iris",
                        "roles": [
                            {
                                "name": "observer"
                            }
                        ]
                    }
                ]
            }
        ], 
        "remote": [
            {
                "type": "OIDC-preferred_username"
            }, 
            {
                "type": "OIDC-email"
            }, 
            {
                "regex": true, 
                "type": "OIDC-email",
                "any_one_of": [
                    "^.*@stackhpc.com$",
                    "^.*@cam.ac.uk$",
                    "^.*.ac.uk$",
                    "daniela.bauer@imperial.ac.uk",
                    "simon.fayer05@imperial.ac.uk",
                    "daniela.bauer.grid@googlemail.com",
                    "markholliman@gmail.com",
                    "nigelhambly@googlemail.com",
		    "yrvafhom@gmail.com",
                    "andrew.mcnab@cern.ch",
		    "e.gonzalezsolares@gmail.com",
		    "andrew.lahiff@gmail.com"
                ]
            }
        ]
    }
]
